BdrcDbLib/DBConfig.py
BdrcDbLib/DbApp.py
BdrcDbLib/DbAppParser.py
BdrcDbLib/SprocColumnError.py
BdrcDbLib/SqlAlchemy_get_or_create.py
BdrcDbLib/__init__.py
BdrcDbLib/DbOrm/DrsContextBase.py
BdrcDbLib/DbOrm/__init__.py
BdrcDbLib/DbOrm/models/DrsProjectManager.py
BdrcDbLib/DbOrm/models/__init__.py
BdrcDbLib/DbOrm/models/drs.py
Tests/DBConfigTest.py
Tests/__init__.py
Tests/test_drs.py
bdrc_db_lib-1.0.23.dist-info/METADATA
bdrc_db_lib-1.0.23.dist-info/WHEEL
bdrc_db_lib-1.0.23.dist-info/top_level.txt
bdrc_db_lib-1.0.23.dist-info/RECORD
