Metadata-Version: 2.2
Name: bdrc-db-lib
Version: 1.0.23
Summary: BDRC Db Library
Home-page: 
Author: jimk
Author-email: jimk <jimk@tbrc.org>
Classifier: Programming Language :: Python :: 3
Classifier: License :: OSI Approved :: MIT License
Classifier: Operating System :: OS Independent
Classifier: Development Status :: 5 - Production/Stable
Requires-Python: >=3.9
Requires-Dist: pymysql
Requires-Dist: lxml
Requires-Dist: sqlalchemy~=1.4.0
Requires-Dist: mysqlclient
Dynamic: author
Dynamic: requires-python
